bss/__init__.py
bss/cbm_stats.py
bss/colormaps.py
bss/dfcio.py
bss/dfsio.py
bss/excepts.py
bss/labeldesc_io.py
bss/math_ops.py
bss/modelspec.py
bss/mpl_import.py
bss/nii_io.py
bss/nimgdata_io.py
bss/rimport.py
bss/rmodels.py
bss/roi_io.py
bss/roi_stats.py
bss/stats_data.py
bss/stats_engine.py
bss/stats_mult_comp.py
bss/stats_nimg_output.py
bss/stats_output.py
bss/stats_result.py
bss/stats_roi_result.py
bss/stats_roidata.py
bss/stats_vertex_output.py
bss/surfio.py
bss/tbm_stats.py
bss/utils.py
bss/version.py
bss/conf/__init__.py
bss/conf/brainsuite_labeldescriptions_14May2014.xml
bss/conf/swm_colin_roi_id.csv
bss-0.9.4.data/scripts/bss_append_swm_to_roistat.py
bss-0.9.4.data/scripts/bss_config.py
bss-0.9.4.data/scripts/bss_convert_surface.py
bss-0.9.4.data/scripts/bss_create_modelspec.py
bss-0.9.4.data/scripts/bss_export_data.py
bss-0.9.4.data/scripts/bss_fdr.py
bss-0.9.4.data/scripts/bss_image_to_shape.py
bss-0.9.4.data/scripts/bss_mean_surface.py
bss-0.9.4.data/scripts/bss_ops.py
bss-0.9.4.data/scripts/bss_prepare_data_for_cbm.py
bss-0.9.4.data/scripts/bss_prepare_data_for_roi.py
bss-0.9.4.data/scripts/bss_prepare_data_for_tbm.py
bss-0.9.4.data/scripts/bss_resample_surface_to_target.py
bss-0.9.4.data/scripts/bss_roi.py
bss-0.9.4.data/scripts/bss_roi_sphere_to_mask.py
bss-0.9.4.data/scripts/bss_run.py
bss-0.9.4.data/scripts/bss_save_roi_mean.py
bss-0.9.4.data/scripts/bss_save_roistats2csv.py
bss-0.9.4.data/scripts/bss_write_attrib_to_surface.py
bss-0.9.4.data/scripts/bss_write_pvalue_as_color.py
bss-0.9.4.data/scripts/paired_t_test_shape.py
bss-0.9.4.dist-info/DESCRIPTION.rst
bss-0.9.4.dist-info/LICENSE.txt
bss-0.9.4.dist-info/METADATA
bss-0.9.4.dist-info/RECORD
bss-0.9.4.dist-info/WHEEL
bss-0.9.4.dist-info/metadata.json
bss-0.9.4.dist-info/top_level.txt
